{"municipio":{"CODIGOINE":"03064000000","ID_REL":"1030648","COD_GEO":"03315","CODPROV":"03","NOMBRE_PROVINCIA":"Alacant\/Alicante","NOMBRE":"Dolores","POBLACION_MUNI":7237,"SUPERFICIE":1870.1083,"PERIMETRO":21304,"CODIGOINE_CAPITAL":"03064000101","NOMBRE_CAPITAL":"Dolores","POBLACION_CAPITAL":"6080","HOJA_MTN25":"0914-1","LONGITUD_ETRS89_REGCAN95":-0.76969869,"LATITUD_ETRS89_REGCAN95":38.13897736,"ORIGEN_COORD":"Mapa","ALTITUD":4,"ORIGEN_ALTITUD":"MDT5","DISCREPANTE_INE":0},"fecha":"2021-12-01","stateSky":{"description":"Despejado","id":"11"},"temperatura_actual":"18","temperaturas":{"max":"19","min":"7"},"humedad":"32","viento":"12","lluvia":"0","imagen":null,"pronostico":{"hoy":{"@attributes":{"fecha":"2021-12-01","orto":"08:00","ocaso":"17:43"},"estado_cielo":["11n","11n","11","11","11","11","11","11","11","11","17","17n","17n","17n","15n","16n","16n"],"precipitacion":["0","0","0","0","0","0","0","0","0","0","0","0","0","0","0","0","0"],"prob_precipitacion":["0","0","0"],"prob_tormenta":["0","0","0"],"nieve":["0","0","0","0","0","0","0","0","0","0","0","0","0","0","0","0","0"],"prob_nieve":["0","0","0"],"temperatura":["8","9","11","13","15","18","18","18","18","17","15","13","13","13","14","13"],"sens_termica":["8","9","11","13","15","18","18","18","18","17","15","13","13","13","14","13"],"humedad_relativa":["68","67","69","60","51","41","35","31","32","40","40","44","44","44","45","46"],"viento":[{"@attributes":{"periodo":"08"},"direccion":"O","velocidad":"7"},{"@attributes":{"periodo":"09"},"direccion":"O","velocidad":"7"},{"@attributes":{"periodo":"10"},"direccion":"O","velocidad":"9"},{"@attributes":{"periodo":"11"},"direccion":"O","velocidad":"16"},{"@attributes":{"periodo":"12"},"direccion":"O","velocidad":"17"},{"@attributes":{"periodo":"13"},"direccion":"O","velocidad":"15"},{"@attributes":{"periodo":"14"},"direccion":"O","velocidad":"19"},{"@attributes":{"periodo":"15"},"direccion":"SO","velocidad":"15"},{"@attributes":{"periodo":"16"},"direccion":"SO","velocidad":"12"},{"@attributes":{"periodo":"17"},"direccion":"O","velocidad":"10"},{"@attributes":{"periodo":"18"},"direccion":"O","velocidad":"8"},{"@attributes":{"periodo":"19"},"direccion":"SO","velocidad":"6"},{"@attributes":{"periodo":"20"},"direccion":"SO","velocidad":"6"},{"@attributes":{"periodo":"21"},"direccion":"O","velocidad":"11"},{"@attributes":{"periodo":"22"},"direccion":"O","velocidad":"17"},{"@attributes":{"periodo":"23"},"direccion":"O","velocidad":"15"}],"racha_max":["9","14","23","26","25","31","26","19","15","11","8","8","15","23","20","28"]},"manana":{"@attributes":{"fecha":"2021-12-02","orto":"08:01","ocaso":"17:43"},"estado_cielo":["11n","17n","17n","16n","16n","16n","16n","16n","16n","16","14","12","11","12","11","11","11","11","11n","11n","11n","11n","11n","11n"],"precipitacion":["0","0","0","0","0","0","0","0","0","0","0","0","0","0","0","0","0","0","0","0","0","0","0","0"],"prob_precipitacion":["5","0","0","0"],"prob_tormenta":["5","0","0","0"],"nieve":["0","0","0","0","0","0","0","0","0","0","0","0","0","0","0","0","0","0","0","0","0","0","0","0"],"prob_nieve":["0","0","0","0"],"temperatura":["13","13","12","11","12","12","12","12","12","13","13","14","15","16","16","17","17","16","14","13","13","12","12","11"],"sens_termica":["13","13","12","11","12","12","12","12","12","13","13","14","15","16","16","17","17","16","14","13","13","12","12","11"],"humedad_relativa":["47","48","53","59","59","59","63","63","59","56","53","46","41","37","35","33","31","33","29","33","39","42","44","45"],"viento":[{"@attributes":{"periodo":"00"},"direccion":"O","velocidad":"20"},{"@attributes":{"periodo":"01"},"direccion":"O","velocidad":"17"},{"@attributes":{"periodo":"02"},"direccion":"O","velocidad":"16"},{"@attributes":{"periodo":"03"},"direccion":"O","velocidad":"15"},{"@attributes":{"periodo":"04"},"direccion":"O","velocidad":"23"},{"@attributes":{"periodo":"05"},"direccion":"O","velocidad":"24"},{"@attributes":{"periodo":"06"},"direccion":"NO","velocidad":"23"},{"@attributes":{"periodo":"07"},"direccion":"O","velocidad":"19"},{"@attributes":{"periodo":"08"},"direccion":"O","velocidad":"19"},{"@attributes":{"periodo":"09"},"direccion":"O","velocidad":"19"},{"@attributes":{"periodo":"10"},"direccion":"O","velocidad":"13"},{"@attributes":{"periodo":"11"},"direccion":"NO","velocidad":"20"},{"@attributes":{"periodo":"12"},"direccion":"NO","velocidad":"24"},{"@attributes":{"periodo":"13"},"direccion":"NO","velocidad":"24"},{"@attributes":{"periodo":"14"},"direccion":"N","velocidad":"27"},{"@attributes":{"periodo":"15"},"direccion":"N","velocidad":"27"},{"@attributes":{"periodo":"16"},"direccion":"N","velocidad":"24"},{"@attributes":{"periodo":"17"},"direccion":"NO","velocidad":"23"},{"@attributes":{"periodo":"18"},"direccion":"N","velocidad":"19"},{"@attributes":{"periodo":"19"},"direccion":"NO","velocidad":"10"},{"@attributes":{"periodo":"20"},"direccion":"O","velocidad":"13"},{"@attributes":{"periodo":"21"},"direccion":"NO","velocidad":"14"},{"@attributes":{"periodo":"22"},"direccion":"N","velocidad":"30"},{"@attributes":{"periodo":"23"},"direccion":"N","velocidad":"32"}],"racha_max":["24","22","20","35","35","32","28","26","28","19","30","37","37","42","40","37","33","27","14","20","19","43","47","50"]}},"proximos_dias":[{"@attributes":{"fecha":"2021-12-02"},"prob_precipitacion":["5","5","0","5","0","0","0"],"cota_nieve_prov":[{"@attributes":{"periodo":"00-24"}},{"@attributes":{"periodo":"00-12"}},{"@attributes":{"periodo":"12-24"}},{"@attributes":{"periodo":"00-06"}},{"@attributes":{"periodo":"06-12"}},{"@attributes":{"periodo":"12-18"}},{"@attributes":{"periodo":"18-24"}}],"estado_cielo":["12","14","11","14n","14","11","11n"],"viento":[{"@attributes":{"periodo":"00-24"},"direccion":"NO","velocidad":"25"},{"@attributes":{"periodo":"00-12"},"direccion":"NO","velocidad":"25"},{"@attributes":{"periodo":"12-24"},"direccion":"NO","velocidad":"25"},{"@attributes":{"periodo":"00-06"},"direccion":"O","velocidad":"20"},{"@attributes":{"periodo":"06-12"},"direccion":"NO","velocidad":"25"},{"@attributes":{"periodo":"12-18"},"direccion":"NO","velocidad":"10"},{"@attributes":{"periodo":"18-24"},"direccion":"O","velocidad":"10"}],"racha_max":["35","35","35",{"@attributes":{"periodo":"00-06"}},"35",{"@attributes":{"periodo":"12-18"}},{"@attributes":{"periodo":"18-24"}}],"temperatura":{"maxima":"17","minima":"10","dato":["12","16","13","10"]},"sens_termica":{"maxima":"17","minima":"10","dato":["12","16","13","10"]},"humedad_relativa":{"maxima":"65","minima":"30","dato":["65","35","35","35"]},"uv_max":"1"},{"@attributes":{"fecha":"2021-12-03"},"prob_precipitacion":["0","0","0"],"cota_nieve_prov":[{"@attributes":{"periodo":"00-24"}},{"@attributes":{"periodo":"00-12"}},{"@attributes":{"periodo":"12-24"}}],"estado_cielo":["12","12","12"],"viento":[{"@attributes":{"periodo":"00-24"},"direccion":"NO","velocidad":"15"},{"@attributes":{"periodo":"00-12"},"direccion":"NO","velocidad":"25"},{"@attributes":{"periodo":"12-24"},"direccion":"NO","velocidad":"15"}],"racha_max":[{"@attributes":{"periodo":"00-24"}},"45",{"@attributes":{"periodo":"12-24"}}],"temperatura":{"maxima":"18","minima":"8"},"sens_termica":{"maxima":"18","minima":"8"},"humedad_relativa":{"maxima":"65","minima":"35"},"uv_max":"2"},{"@attributes":{"fecha":"2021-12-04"},"prob_precipitacion":["10","0","10"],"cota_nieve_prov":[{"@attributes":{"periodo":"00-24"}},{"@attributes":{"periodo":"00-12"}},{"@attributes":{"periodo":"12-24"}}],"estado_cielo":["13","11","14"],"viento":[{"@attributes":{"periodo":"00-24"},"direccion":"O","velocidad":"15"},{"@attributes":{"periodo":"00-12"},"direccion":"O","velocidad":"15"},{"@attributes":{"periodo":"12-24"},"direccion":"O","velocidad":"15"}],"racha_max":[{"@attributes":{"periodo":"00-24"}},{"@attributes":{"periodo":"00-12"}},{"@attributes":{"periodo":"12-24"}}],"temperatura":{"maxima":"20","minima":"7"},"sens_termica":{"maxima":"20","minima":"7"},"humedad_relativa":{"maxima":"65","minima":"30"},"uv_max":"2"},{"@attributes":{"fecha":"2021-12-05"},"prob_precipitacion":"0","cota_nieve_prov":{},"estado_cielo":"11","viento":{"direccion":"O","velocidad":"20"},"racha_max":"40","temperatura":{"maxima":"18","minima":"9"},"sens_termica":{"maxima":"18","minima":"9"},"humedad_relativa":{"maxima":"65","minima":"30"},"uv_max":"1"},{"@attributes":{"fecha":"2021-12-06"},"prob_precipitacion":"0","cota_nieve_prov":{},"estado_cielo":"14","viento":{"direccion":"NO","velocidad":"15"},"racha_max":{},"temperatura":{"maxima":"19","minima":"9"},"sens_termica":{"maxima":"19","minima":"9"},"humedad_relativa":{"maxima":"60","minima":"40"}},{"@attributes":{"fecha":"2021-12-07"},"prob_precipitacion":"10","cota_nieve_prov":{},"estado_cielo":"13","viento":{"direccion":"O","velocidad":"25"},"racha_max":"50","temperatura":{"maxima":"22","minima":"12"},"sens_termica":{"maxima":"22","minima":"12"},"humedad_relativa":{"maxima":"95","minima":"50"}}],"breadcrumb":[{"name":"Provincias","url":"\/provincias","title":"El tiempo | Lista de provincias"},{"name":"Alacant\/Alicante","url":"\/provincias\/03","title":"El tiempo en la provincia de Alacant\/Alicante"},{"name":"Municipios","url":"\/provincias\/03\/municipios","title":"El tiempo | Lista de municipios de Alacant\/Alicante"},{"name":"Dolores","url":"\/provincias\/03\/municipios\/03315","title":"El tiempo en Dolores"}],"keywords":"Dolores, Provincia de Alicante, previsi\u00f3n meteorol\u00f3gica, previsi\u00f3n del tiempo, Espa\u00f1a, viento, humedad, precipitaciones, lluvia, estado del cielo"}